streammap/__init__.py
streammap/delineate.py
streammap/georef.py
streammap/preprocess.py
streammap/singularity_index.py
streammap/visualization.py
streammap-0.0.1.dist-info/LICENCE
streammap-0.0.1.dist-info/METADATA
streammap-0.0.1.dist-info/WHEEL
streammap-0.0.1.dist-info/top_level.txt
streammap-0.0.1.dist-info/RECORD
