Metadata-Version: 2.1
Name: streammap
Version: 0.0.1
Summary: An automated river analysis and mapping engine.
Home-page: https://github.com/geoapnet/streammap
Author: Yassine Hammoud
Author-email: yassinehammoud@geo-ap.com
Keywords: remote sensing,stream,satellite,river
Classifier: Development Status :: 4 - Beta
Classifier: Programming Language :: Python :: 3.9
Classifier: Operating System :: OS Independent
Classifier: Intended Audience :: Science/Research
Classifier: Intended Audience :: Developers
Classifier: Topic :: Utilities
Classifier: Topic :: Scientific/Engineering :: GIS
Classifier: Topic :: Scientific/Engineering :: Visualization
Classifier: Topic :: Software Development :: Libraries :: Python Modules
License-File: LICENCE
Requires-Dist: numpy
Requires-Dist: scipy
Requires-Dist: matplotlib
Requires-Dist: gdal
Requires-Dist: opencv-python
Requires-Dist: pyshp
